Metadata-Version: 1.0
Name: psd-parvaresh
Version: 0.1
Summary: Power Spectral Density Calculator
Home-page: UNKNOWN
Author: Stephen Parvaresh
Author-email: UNKNOWN
License: UNKNOWN
Platform: UNKNOWN
